parameterpack/__init__.py
parameterpack/helpers.py
parameterpack-0.1.0.dist-info/DESCRIPTION.rst
parameterpack-0.1.0.dist-info/METADATA
parameterpack-0.1.0.dist-info/RECORD
parameterpack-0.1.0.dist-info/WHEEL
parameterpack-0.1.0.dist-info/metadata.json
parameterpack-0.1.0.dist-info/top_level.txt
