Metadata-Version: 2.0
Name: parameterpack
Version: 0.1.0
Summary: Ellipsis trickery for enabling fold expressions
Home-page: https://github.com/TehJoE/parameterpack
Author: Joe Lawson
Author-email: UNKNOWN
License: MIT
Keywords: development fold functional pack unpack
Platform: UNKNOWN
Classifier: Development Status :: 3 - Alpha
Classifier: Intended Audience :: Developers
Classifier: Topic :: Software Development :: Libraries :: Python Modules
Classifier: License :: OSI Approved :: MIT License
Classifier: Programming Language :: Python :: 3
Classifier: Programming Language :: Python :: 3.3
Classifier: Programming Language :: Python :: 3.4
Classifier: Programming Language :: Python :: 3.5
Classifier: Programming Language :: Python :: Implementation :: CPython
Provides-Extra: dev
Requires-Dist: bumpversion; extra == 'dev'
Requires-Dist: tox; extra == 'dev'
